{
    "name": "garagem-da-paulinha",
    "dockerComposeFile": ["../compose.yaml"],
    "service": "app",
    "workspaceFolder": "/app",
    "shutdownAction": "stopCompose",
    "overrideCommand": false,
    "customizations": {
        "vscode": {
            "settings": {
                "terminal.integrated.defaultProfile.linux": "zsh"
            },
            "extensions": [
                "monokai.theme-monokai-pro-vscode",
                "GitHub.copilot",
                "GitHub.copilot-chat",
                "formulahendry.auto-close-tag" // Aquela que deu erro no print
            ]
        }
    }
}